temperaturaconverter/__init__.py
temperaturaconverter/temperaturaConverter.py
temperaturaconverter-0.2.0.dist-info/entry_points.txt
temperaturaconverter-0.2.0.dist-info/WHEEL
temperaturaconverter-0.2.0.dist-info/METADATA
temperaturaconverter-0.2.0.dist-info/RECORD
