Metadata-Version: 2.1
Name: temperaturaconverter
Version: 0.2.0
Summary: 
Author: chjuca
Author-email: chjuca@utpl.edu.ec
Requires-Python: >=3.8,<4.0
Classifier: Programming Language :: Python :: 3
Classifier: Programming Language :: Python :: 3.8
Classifier: Programming Language :: Python :: 3.9
Requires-Dist: click (>=8.0.1,<9.0.0)
Requires-Dist: twine (>=3.4.1,<4.0.0)
